{
  "version": "7",
  "dialect": "postgresql",
  "entries": [
    {
      "idx": 0,
      "version": "7",
      "when": 1774967582960,
      "tag": "0000_many_anthem",
      "breakpoints": true
    },
    {
      "idx": 1,
      "version": "7",
      "when": 1775065356946,
      "tag": "0001_remarkable_callisto",
      "breakpoints": true
    },
    {
      "idx": 2,
      "version": "7",
      "when": 1775765601221,
      "tag": "0002_easy_stellaris",
      "breakpoints": true
    },
    {
      "idx": 3,
      "version": "7",
      "when": 1775950456411,
      "tag": "0003_charming_baron_zemo",
      "breakpoints": true
    }
  ]
}